bot_rickroll/__init__.py
bot_rickroll/settings.py
bot_rickroll/urls.py
bot_rickroll/views.py
django_bot_rickroll-0.3.0.dist-info/WHEEL
django_bot_rickroll-0.3.0.dist-info/METADATA
django_bot_rickroll-0.3.0.dist-info/RECORD
