Metadata-Version: 2.4
Name: django-bot-rickroll
Version: 0.3.0
Summary: Django plugin that rickrolls bots and scanners by redirecting common malicious URLs
Keywords: django,security,rickroll,bots,scanners
License-Expression: MIT
Classifier: Development Status :: 4 - Beta
Classifier: Framework :: Django
Classifier: Framework :: Django :: 4.0
Classifier: Framework :: Django :: 4.1
Classifier: Framework :: Django :: 4.2
Classifier: Framework :: Django :: 5.0
Classifier: Framework :: Django :: 5.1
Classifier: Intended Audience :: Developers
Classifier: License :: OSI Approved :: MIT License
Classifier: Operating System :: OS Independent
Classifier: Programming Language :: Python :: 3
Classifier: Programming Language :: Python :: 3.11
Classifier: Programming Language :: Python :: 3.12
Classifier: Programming Language :: Python :: 3.13
Classifier: Topic :: Internet :: WWW/HTTP
Classifier: Topic :: Security
Requires-Dist: django>=4.0
Requires-Python: >=3.11
Project-URL: Homepage, https://github.com/vEnhance/django-bot-rickroll
Project-URL: Repository, https://github.com/vEnhance/django-bot-rickroll
